<?xml version="1.0" encoding="UTF-8"?>
  <rdw211:FluidsReport uuid="" schemaVersion="" objectVersion="">
   <rdw212:Aliases xsi:type="rdw212:ObjectAlias" authority="">
    <rdw212:Identifier xsi:type="rdw212:String64"></rdw212:Identifier>
    <rdw212:IdentifierKind xsi:type="rdw212:AliasIdentifierKindExt"></rdw212:IdentifierKind>
    <rdw212:Description xsi:type="rdw212:String2000"></rdw212:Description>
    <rdw212:EffectiveDateTime xsi:type="rdw212:TimeStamp">2026-01-05T19:39:47Z</rdw212:EffectiveDateTime>
    <rdw212:TerminationDateTime xsi:type="rdw212:TimeStamp">2026-01-05T19:39:47Z</rdw212:TerminationDateTime>
   </rdw212:Aliases>
   <rdw212:Citation xsi:type="rdw212:Citation">
    <rdw212:Title xsi:type="rdw212:String256"></rdw212:Title>
    <rdw212:Originator xsi:type="rdw212:String64"></rdw212:Originator>
    <rdw212:Creation xsi:type="rdw212:TimeStamp">2026-01-05T19:39:47Z</rdw212:Creation>
    <rdw212:Format xsi:type="rdw212:String2000"></rdw212:Format>
    <rdw212:Editor xsi:type="rdw212:String64"></rdw212:Editor>
    <rdw212:LastUpdate xsi:type="rdw212:TimeStamp">2026-01-05T19:39:47Z</rdw212:LastUpdate>
    <rdw212:Description xsi:type="rdw212:String2000"></rdw212:Description>
    <rdw212:EditorHistory xsi:type="rdw212:String64"></rdw212:EditorHistory>
    <rdw212:DescriptiveKeywords xsi:type="rdw212:String2000"></rdw212:DescriptiveKeywords>
   </rdw212:Citation>
   <rdw212:Existence xsi:type="rdw212:ExistenceKindExt"></rdw212:Existence>
   <rdw212:ObjectVersionReason xsi:type="rdw212:String2000"></rdw212:ObjectVersionReason>
   <rdw212:BusinessActivityHistory xsi:type="rdw212:String64"></rdw212:BusinessActivityHistory>
   <rdw212:OSDUIntegration xsi:type="rdw212:OSDUIntegration">
    <rdw212:LineageAssertions xsi:type="rdw212:OSDULineageAssertion">
     <rdw212:ID xsi:type="rdw212:String256"></rdw212:ID>
     <rdw212:LineageRelationshipKind xsi:type="rdw212:OSDULineageRelationshipKind">direct</rdw212:LineageRelationshipKind>
    </rdw212:LineageAssertions>
    <rdw212:OwnerGroup xsi:type="rdw212:String256"></rdw212:OwnerGroup>
    <rdw212:ViewerGroup xsi:type="rdw212:String256"></rdw212:ViewerGroup>
    <rdw212:LegalTags xsi:type="rdw212:String256"></rdw212:LegalTags>
    <rdw212:OSDUGeoJSON xsi:type="xsd:string"></rdw212:OSDUGeoJSON>
    <rdw212:WGS84Latitude xsi:type="rdw212:PlaneAngleMeasure" uom="0.001 seca">0.0</rdw212:WGS84Latitude>
    <rdw212:WGS84Longitude xsi:type="rdw212:PlaneAngleMeasure" uom="0.001 seca">0.0</rdw212:WGS84Longitude>
    <rdw212:WGS84LocationMetadata xsi:type="rdw212:OSDUSpatialLocationIntegration">
     <rdw212:SpatialLocationCoordinatesDate xsi:type="rdw212:TimeStamp">2026-01-05T19:39:47Z</rdw212:SpatialLocationCoordinatesDate>
     <rdw212:QuantitativeAccuracyBand xsi:type="rdw212:String64"></rdw212:QuantitativeAccuracyBand>
     <rdw212:QualitativeSpatialAccuracyType xsi:type="rdw212:String64"></rdw212:QualitativeSpatialAccuracyType>
     <rdw212:CoordinateQualityCheckPerformedBy xsi:type="rdw212:String64"></rdw212:CoordinateQualityCheckPerformedBy>
     <rdw212:CoordinateQualityCheckDateTime xsi:type="rdw212:TimeStamp">2026-01-05T19:39:47Z</rdw212:CoordinateQualityCheckDateTime>
     <rdw212:CoordinateQualityCheckRemark xsi:type="rdw212:String256"></rdw212:CoordinateQualityCheckRemark>
     <rdw212:AppliedOperation xsi:type="rdw212:String256"></rdw212:AppliedOperation>
    </rdw212:WGS84LocationMetadata>
    <rdw212:Field xsi:type="rdw212:String64"></rdw212:Field>
    <rdw212:Country xsi:type="rdw212:String64"></rdw212:Country>
    <rdw212:State xsi:type="rdw212:String64"></rdw212:State>
    <rdw212:County xsi:type="rdw212:String64"></rdw212:County>
    <rdw212:City xsi:type="rdw212:String64"></rdw212:City>
    <rdw212:Region xsi:type="rdw212:String64"></rdw212:Region>
    <rdw212:District xsi:type="rdw212:String64"></rdw212:District>
    <rdw212:Block xsi:type="rdw212:String64"></rdw212:Block>
    <rdw212:Prospect xsi:type="rdw212:String64"></rdw212:Prospect>
    <rdw212:Play xsi:type="rdw212:String64"></rdw212:Play>
    <rdw212:Basin xsi:type="rdw212:String64"></rdw212:Basin>
   </rdw212:OSDUIntegration>
   <rdw212:CustomData xsi:type="rdw212:CustomData">
    <!-- extensibility element(s) -->
   </rdw212:CustomData>
   <rdw212:ExtensionNameValue xsi:type="rdw212:ExtensionNameValue">
    <rdw212:Name xsi:type="rdw212:String64"></rdw212:Name>
    <rdw212:Value xsi:type="rdw212:StringMeasure" uom=""></rdw212:Value>
    <rdw212:MeasureClass xsi:type="rdw212:MeasureClass">absorbed dose</rdw212:MeasureClass>
    <rdw212:DTim xsi:type="rdw212:TimeStamp">2026-01-05T19:39:47Z</rdw212:DTim>
    <rdw212:Index xsi:type="xsd:long">0</rdw212:Index>
    <rdw212:Description xsi:type="rdw212:String2000"></rdw212:Description>
   </rdw212:ExtensionNameValue>
   <rdw211:DTim xsi:type="rdw212:TimeStamp">2026-01-05T19:39:47Z</rdw211:DTim>
   <rdw211:Md xsi:type="rdw212:MeasuredDepth">
    <rdw212:MeasuredDepth xsi:type="rdw212:LengthMeasureExt" uom="">0.0</rdw212:MeasuredDepth>
    <rdw212:Datum xsi:type="rdw212:DataObjectReference">
     <rdw212:Uuid xsi:type="rdw212:UuidString"></rdw212:Uuid>
     <rdw212:ObjectVersion xsi:type="rdw212:String64"></rdw212:ObjectVersion>
     <rdw212:QualifiedType xsi:type="rdw212:QualifiedType"></rdw212:QualifiedType>
     <rdw212:Title xsi:type="rdw212:String2000"></rdw212:Title>
     <rdw212:EnergisticsUri xsi:type="xsd:anyURI">http://www.example.com/schema/anyURI</rdw212:EnergisticsUri>
     <rdw212:LocatorUrl xsi:type="xsd:anyURI">http://www.example.com/schema/anyURI</rdw212:LocatorUrl>
     <rdw212:ExtensionNameValue xsi:type="rdw212:ExtensionNameValue">
      <rdw212:Name xsi:type="rdw212:String64"></rdw212:Name>
      <rdw212:Value xsi:type="rdw212:StringMeasure" uom=""></rdw212:Value>
      <rdw212:MeasureClass xsi:type="rdw212:MeasureClass">absorbed dose</rdw212:MeasureClass>
      <rdw212:DTim xsi:type="rdw212:TimeStamp">2026-01-05T19:39:47Z</rdw212:DTim>
      <rdw212:Index xsi:type="xsd:long">0</rdw212:Index>
      <rdw212:Description xsi:type="rdw212:String2000"></rdw212:Description>
     </rdw212:ExtensionNameValue>
    </rdw212:Datum>
   </rdw211:Md>
   <rdw211:Tvd xsi:type="rdw212:AbstractVerticalDepth">
    <rdw212:VerticalDepth xsi:type="rdw212:LengthMeasureExt" uom="">0.0</rdw212:VerticalDepth>
    <rdw212:Trajectory xsi:type="rdw212:DataObjectReference">
     <rdw212:Uuid xsi:type="rdw212:UuidString"></rdw212:Uuid>
     <rdw212:ObjectVersion xsi:type="rdw212:String64"></rdw212:ObjectVersion>
     <rdw212:QualifiedType xsi:type="rdw212:QualifiedType"></rdw212:QualifiedType>
     <rdw212:Title xsi:type="rdw212:String2000"></rdw212:Title>
     <rdw212:EnergisticsUri xsi:type="xsd:anyURI">http://www.example.com/schema/anyURI</rdw212:EnergisticsUri>
     <rdw212:LocatorUrl xsi:type="xsd:anyURI">http://www.example.com/schema/anyURI</rdw212:LocatorUrl>
     <rdw212:ExtensionNameValue xsi:type="rdw212:ExtensionNameValue">
      <rdw212:Name xsi:type="rdw212:String64"></rdw212:Name>
      <rdw212:Value xsi:type="rdw212:StringMeasure" uom=""></rdw212:Value>
      <rdw212:MeasureClass xsi:type="rdw212:MeasureClass">absorbed dose</rdw212:MeasureClass>
      <rdw212:DTim xsi:type="rdw212:TimeStamp">2026-01-05T19:39:47Z</rdw212:DTim>
      <rdw212:Index xsi:type="xsd:long">0</rdw212:Index>
      <rdw212:Description xsi:type="rdw212:String2000"></rdw212:Description>
     </rdw212:ExtensionNameValue>
    </rdw212:Trajectory>
   </rdw211:Tvd>
   <rdw211:NumReport xsi:type="xsd:long">0</rdw211:NumReport>
   <rdw211:Fluid xsi:type="rdw211:Fluid" uid="">
    <rdw211:Type xsi:type="rdw212:String64"></rdw211:Type>
    <rdw211:LocationSample xsi:type="rdw212:String64"></rdw211:LocationSample>
    <rdw211:DTim xsi:type="rdw212:TimeStamp">2026-01-05T19:39:47Z</rdw211:DTim>
    <rdw211:Md xsi:type="rdw212:MeasuredDepth">
     <rdw212:MeasuredDepth xsi:type="rdw212:LengthMeasureExt" uom="">0.0</rdw212:MeasuredDepth>
     <rdw212:Datum xsi:type="rdw212:DataObjectReference">
      <rdw212:Uuid xsi:type="rdw212:UuidString"></rdw212:Uuid>
      <rdw212:ObjectVersion xsi:type="rdw212:String64"></rdw212:ObjectVersion>
      <rdw212:QualifiedType xsi:type="rdw212:QualifiedType"></rdw212:QualifiedType>
      <rdw212:Title xsi:type="rdw212:String2000"></rdw212:Title>
      <rdw212:EnergisticsUri xsi:type="xsd:anyURI">http://www.example.com/schema/anyURI</rdw212:EnergisticsUri>
      <rdw212:LocatorUrl xsi:type="xsd:anyURI">http://www.example.com/schema/anyURI</rdw212:LocatorUrl>
      <rdw212:ExtensionNameValue xsi:type="rdw212:ExtensionNameValue">
       <rdw212:Name xsi:type="rdw212:String64"></rdw212:Name>
       <rdw212:Value xsi:type="rdw212:StringMeasure" uom=""></rdw212:Value>
       <rdw212:MeasureClass xsi:type="rdw212:MeasureClass">absorbed dose</rdw212:MeasureClass>
       <rdw212:DTim xsi:type="rdw212:TimeStamp">2026-01-05T19:39:47Z</rdw212:DTim>
       <rdw212:Index xsi:type="xsd:long">0</rdw212:Index>
       <rdw212:Description xsi:type="rdw212:String2000"></rdw212:Description>
      </rdw212:ExtensionNameValue>
     </rdw212:Datum>
    </rdw211:Md>
    <rdw211:Tvd xsi:type="rdw212:AbstractVerticalDepth">
     <rdw212:VerticalDepth xsi:type="rdw212:LengthMeasureExt" uom="">0.0</rdw212:VerticalDepth>
     <rdw212:Trajectory xsi:type="rdw212:DataObjectReference">
      <rdw212:Uuid xsi:type="rdw212:UuidString"></rdw212:Uuid>
      <rdw212:ObjectVersion xsi:type="rdw212:String64"></rdw212:ObjectVersion>
      <rdw212:QualifiedType xsi:type="rdw212:QualifiedType"></rdw212:QualifiedType>
      <rdw212:Title xsi:type="rdw212:String2000"></rdw212:Title>
      <rdw212:EnergisticsUri xsi:type="xsd:anyURI">http://www.example.com/schema/anyURI</rdw212:EnergisticsUri>
      <rdw212:LocatorUrl xsi:type="xsd:anyURI">http://www.example.com/schema/anyURI</rdw212:LocatorUrl>
      <rdw212:ExtensionNameValue xsi:type="rdw212:ExtensionNameValue">
       <rdw212:Name xsi:type="rdw212:String64"></rdw212:Name>
       <rdw212:Value xsi:type="rdw212:StringMeasure" uom=""></rdw212:Value>
       <rdw212:MeasureClass xsi:type="rdw212:MeasureClass">absorbed dose</rdw212:MeasureClass>
       <rdw212:DTim xsi:type="rdw212:TimeStamp">2026-01-05T19:39:47Z</rdw212:DTim>
       <rdw212:Index xsi:type="xsd:long">0</rdw212:Index>
       <rdw212:Description xsi:type="rdw212:String2000"></rdw212:Description>
      </rdw212:ExtensionNameValue>
     </rdw212:Trajectory>
    </rdw211:Tvd>
    <rdw211:Ecd xsi:type="rdw212:MassPerVolumeMeasure" uom="">0.0</rdw211:Ecd>
    <rdw211:KickToleranceVolume xsi:type="rdw212:VolumeMeasure" uom="">0.0</rdw211:KickToleranceVolume>
    <rdw211:KickToleranceIntensity xsi:type="rdw212:MassPerVolumeMeasure" uom="">0.0</rdw211:KickToleranceIntensity>
    <rdw211:TempFlowLine xsi:type="rdw212:ThermodynamicTemperatureMeasure" uom="K">0.0</rdw211:TempFlowLine>
    <rdw211:PresBopRating xsi:type="rdw212:PressureMeasure" uom="">0.0</rdw211:PresBopRating>
    <rdw211:MudClass xsi:type="rdw211:MudClass">oil-based</rdw211:MudClass>
    <rdw211:Density xsi:type="rdw212:MassPerVolumeMeasure" uom="">0.0</rdw211:Density>
    <rdw211:VisFunnel xsi:type="rdw212:TimeMeasure" uom="a">0.0</rdw211:VisFunnel>
    <rdw211:TempVis xsi:type="rdw212:ThermodynamicTemperatureMeasure" uom="K">0.0</rdw211:TempVis>
    <rdw211:Pv xsi:type="rdw212:DynamicViscosityMeasure" uom="P">0.0</rdw211:Pv>
    <rdw211:Yp xsi:type="rdw212:PressureMeasure" uom="">0.0</rdw211:Yp>
    <rdw211:Gel3Sec xsi:type="rdw212:PressureMeasureExt" uom="">0.0</rdw211:Gel3Sec>
    <rdw211:Gel6Sec xsi:type="rdw212:PressureMeasureExt" uom="">0.0</rdw211:Gel6Sec>
    <rdw211:Gel10Sec xsi:type="rdw212:PressureMeasure" uom="">0.0</rdw211:Gel10Sec>
    <rdw211:Gel10Min xsi:type="rdw212:PressureMeasure" uom="">0.0</rdw211:Gel10Min>
    <rdw211:Gel30Min xsi:type="rdw212:PressureMeasure" uom="">0.0</rdw211:Gel30Min>
    <rdw211:FilterCakeLtlp xsi:type="rdw212:LengthMeasure" uom="m">0.0</rdw211:FilterCakeLtlp>
    <rdw211:FiltrateLtlp xsi:type="rdw212:VolumeMeasure" uom="">0.0</rdw211:FiltrateLtlp>
    <rdw211:TempHthp xsi:type="rdw212:ThermodynamicTemperatureMeasure" uom="K">0.0</rdw211:TempHthp>
    <rdw211:PresHthp xsi:type="rdw212:PressureMeasure" uom="">0.0</rdw211:PresHthp>
    <rdw211:FiltrateHthp xsi:type="rdw212:VolumeMeasure" uom="">0.0</rdw211:FiltrateHthp>
    <rdw211:FilterCakeHthp xsi:type="rdw212:LengthMeasure" uom="m">0.0</rdw211:FilterCakeHthp>
    <rdw211:SolidsPc xsi:type="rdw212:VolumePerVolumeMeasure" uom="">0.0</rdw211:SolidsPc>
    <rdw211:WaterPc xsi:type="rdw212:VolumePerVolumeMeasure" uom="">0.0</rdw211:WaterPc>
    <rdw211:OilPc xsi:type="rdw212:VolumePerVolumeMeasure" uom="">0.0</rdw211:OilPc>
    <rdw211:SandPc xsi:type="rdw212:VolumePerVolumeMeasure" uom="">0.0</rdw211:SandPc>
    <rdw211:SolidsLowGravPc xsi:type="rdw212:VolumePerVolumeMeasure" uom="">0.0</rdw211:SolidsLowGravPc>
    <rdw211:SolidsLowGrav xsi:type="rdw212:MassPerVolumeMeasure" uom="">0.0</rdw211:SolidsLowGrav>
    <rdw211:SolidsCalcPc xsi:type="rdw212:VolumePerVolumeMeasure" uom="">0.0</rdw211:SolidsCalcPc>
    <rdw211:BaritePc xsi:type="rdw212:VolumePerVolumeMeasure" uom="">0.0</rdw211:BaritePc>
    <rdw211:Lcm xsi:type="rdw212:MassPerVolumeMeasure" uom="">0.0</rdw211:Lcm>
    <rdw211:Mbt xsi:type="rdw212:CationExchangeCapacityMeasureExt" uom="">0.0</rdw211:Mbt>
    <rdw211:Ph xsi:type="xsd:double">0.0</rdw211:Ph>
    <rdw211:TempPh xsi:type="rdw212:ThermodynamicTemperatureMeasure" uom="K">0.0</rdw211:TempPh>
    <rdw211:Pm xsi:type="rdw212:VolumeMeasure" uom="">0.0</rdw211:Pm>
    <rdw211:PmFiltrate xsi:type="rdw212:VolumeMeasure" uom="">0.0</rdw211:PmFiltrate>
    <rdw211:Mf xsi:type="rdw212:VolumeMeasure" uom="">0.0</rdw211:Mf>
    <rdw211:AlkalinityP1 xsi:type="rdw212:VolumeMeasure" uom="">0.0</rdw211:AlkalinityP1>
    <rdw211:AlkalinityP2 xsi:type="rdw212:VolumeMeasure" uom="">0.0</rdw211:AlkalinityP2>
    <rdw211:Chloride xsi:type="rdw212:MassPerVolumeMeasure" uom="">0.0</rdw211:Chloride>
    <rdw211:Calcium xsi:type="rdw212:MassPerVolumeMeasure" uom="">0.0</rdw211:Calcium>
    <rdw211:Magnesium xsi:type="rdw212:MassPerVolumeMeasure" uom="">0.0</rdw211:Magnesium>
    <rdw211:Potassium xsi:type="rdw212:MassPerVolumeMeasure" uom="">0.0</rdw211:Potassium>
    <rdw211:BrinePc xsi:type="rdw212:VolumePerVolumeMeasure" uom="">0.0</rdw211:BrinePc>
    <rdw211:BrineDensity xsi:type="rdw212:MassPerVolumeMeasure" uom="">0.0</rdw211:BrineDensity>
    <rdw211:BrineClass xsi:type="rdw211:BrineClassExt"></rdw211:BrineClass>
    <rdw211:Lime xsi:type="rdw212:MassPerVolumeMeasure" uom="">0.0</rdw211:Lime>
    <rdw211:ElectStab xsi:type="rdw212:ElectricPotentialDifferenceMeasure" uom="V">0.0</rdw211:ElectStab>
    <rdw211:CalciumChloridePc xsi:type="rdw212:VolumePerVolumeMeasure" uom="">0.0</rdw211:CalciumChloridePc>
    <rdw211:CalciumChloride xsi:type="rdw212:MassPerVolumeMeasure" uom="">0.0</rdw211:CalciumChloride>
    <rdw211:Company xsi:type="rdw212:DataObjectReference">
     <rdw212:Uuid xsi:type="rdw212:UuidString"></rdw212:Uuid>
     <rdw212:ObjectVersion xsi:type="rdw212:String64"></rdw212:ObjectVersion>
     <rdw212:QualifiedType xsi:type="rdw212:QualifiedType"></rdw212:QualifiedType>
     <rdw212:Title xsi:type="rdw212:String2000"></rdw212:Title>
     <rdw212:EnergisticsUri xsi:type="xsd:anyURI">http://www.example.com/schema/anyURI</rdw212:EnergisticsUri>
     <rdw212:LocatorUrl xsi:type="xsd:anyURI">http://www.example.com/schema/anyURI</rdw212:LocatorUrl>
     <rdw212:ExtensionNameValue xsi:type="rdw212:ExtensionNameValue">
      <rdw212:Name xsi:type="rdw212:String64"></rdw212:Name>
      <rdw212:Value xsi:type="rdw212:StringMeasure" uom=""></rdw212:Value>
      <rdw212:MeasureClass xsi:type="rdw212:MeasureClass">absorbed dose</rdw212:MeasureClass>
      <rdw212:DTim xsi:type="rdw212:TimeStamp">2026-01-05T19:39:47Z</rdw212:DTim>
      <rdw212:Index xsi:type="xsd:long">0</rdw212:Index>
      <rdw212:Description xsi:type="rdw212:String2000"></rdw212:Description>
     </rdw212:ExtensionNameValue>
    </rdw211:Company>
    <rdw211:Engineer xsi:type="rdw212:String64"></rdw211:Engineer>
    <rdw211:Asg xsi:type="rdw212:MassPerMassMeasure" uom="%">0.0</rdw211:Asg>
    <rdw211:SolidsHiGravPc xsi:type="rdw212:VolumePerVolumeMeasure" uom="">0.0</rdw211:SolidsHiGravPc>
    <rdw211:SolidsHiGrav xsi:type="rdw212:MassPerVolumeMeasure" uom="">0.0</rdw211:SolidsHiGrav>
    <rdw211:Polymer xsi:type="rdw212:VolumePerVolumeMeasure" uom="">0.0</rdw211:Polymer>
    <rdw211:PolyType xsi:type="rdw212:String64"></rdw211:PolyType>
    <rdw211:SolCorPc xsi:type="rdw212:VolumePerVolumeMeasure" uom="">0.0</rdw211:SolCorPc>
    <rdw211:OilCtg xsi:type="rdw212:MassPerMassMeasure" uom="%">0.0</rdw211:OilCtg>
    <rdw211:OilCtgDry xsi:type="rdw212:MassPerVolumeMeasure" uom="">0.0</rdw211:OilCtgDry>
    <rdw211:HardnessCa xsi:type="rdw212:MassPerMassMeasure" uom="%">0.0</rdw211:HardnessCa>
    <rdw211:Sulfide xsi:type="rdw212:MassPerVolumeMeasure" uom="">0.0</rdw211:Sulfide>
    <rdw211:AverageCuttingSize xsi:type="rdw212:LengthMeasure" uom="m">0.0</rdw211:AverageCuttingSize>
    <rdw211:Carbonate xsi:type="rdw212:MassPerVolumeMeasure" uom="">0.0</rdw211:Carbonate>
    <rdw211:Iron xsi:type="rdw212:MassPerVolumeMeasure" uom="">0.0</rdw211:Iron>
    <rdw211:MetalRecovered xsi:type="rdw212:MassMeasure" uom="g">0.0</rdw211:MetalRecovered>
    <rdw211:Turbidity xsi:type="xsd:double">0.0</rdw211:Turbidity>
    <rdw211:OilGrease xsi:type="rdw212:MassPerVolumeMeasure" uom="">0.0</rdw211:OilGrease>
    <rdw211:Salt xsi:type="rdw212:MassPerVolumeMeasure" uom="">0.0</rdw211:Salt>
    <rdw211:SaltPc xsi:type="rdw212:VolumePerVolumeMeasure" uom="">0.0</rdw211:SaltPc>
    <rdw211:Tct xsi:type="rdw212:ThermodynamicTemperatureMeasure" uom="K">0.0</rdw211:Tct>
    <rdw211:WaterPhaseSalinity xsi:type="rdw212:MassPerVolumeMeasure" uom="">0.0</rdw211:WaterPhaseSalinity>
    <rdw211:WholeMudCalcium xsi:type="rdw212:MassPerVolumeMeasure" uom="">0.0</rdw211:WholeMudCalcium>
    <rdw211:WholeMudChloride xsi:type="rdw212:MassPerVolumeMeasure" uom="">0.0</rdw211:WholeMudChloride>
    <rdw211:ZincOxide xsi:type="rdw212:MassPerVolumeMeasure" uom="">0.0</rdw211:ZincOxide>
    <rdw211:SodiumChloride xsi:type="rdw212:MassPerVolumeMeasure" uom="">0.0</rdw211:SodiumChloride>
    <rdw211:SodiumChloridePc xsi:type="rdw212:VolumePerVolumeMeasure" uom="">0.0</rdw211:SodiumChloridePc>
    <rdw211:PptSpurtLoss xsi:type="rdw212:VolumeMeasureExt" uom="">0.0</rdw211:PptSpurtLoss>
    <rdw211:PptPressure xsi:type="rdw212:PressureMeasureExt" uom="">0.0</rdw211:PptPressure>
    <rdw211:PptTemperature xsi:type="rdw212:ThermodynamicTemperatureMeasureExt" uom="">0.0</rdw211:PptTemperature>
    <rdw211:Comments xsi:type="rdw212:String2000"></rdw211:Comments>
    <rdw211:ExtensionNameValue xsi:type="rdw212:ExtensionNameValue">
     <rdw212:Name xsi:type="rdw212:String64"></rdw212:Name>
     <rdw212:Value xsi:type="rdw212:StringMeasure" uom=""></rdw212:Value>
     <rdw212:MeasureClass xsi:type="rdw212:MeasureClass">absorbed dose</rdw212:MeasureClass>
     <rdw212:DTim xsi:type="rdw212:TimeStamp">2026-01-05T19:39:47Z</rdw212:DTim>
     <rdw212:Index xsi:type="xsd:long">0</rdw212:Index>
     <rdw212:Description xsi:type="rdw212:String2000"></rdw212:Description>
    </rdw211:ExtensionNameValue>
    <rdw211:Rheometer xsi:type="rdw211:Rheometer" uid="">
     <rdw211:TempRheom xsi:type="rdw212:ThermodynamicTemperatureMeasure" uom="K">0.0</rdw211:TempRheom>
     <rdw211:PresRheom xsi:type="rdw212:PressureMeasure" uom="">0.0</rdw211:PresRheom>
     <rdw211:ExtensionNameValue xsi:type="rdw212:ExtensionNameValue">
      <rdw212:Name xsi:type="rdw212:String64"></rdw212:Name>
      <rdw212:Value xsi:type="rdw212:StringMeasure" uom=""></rdw212:Value>
      <rdw212:MeasureClass xsi:type="rdw212:MeasureClass">absorbed dose</rdw212:MeasureClass>
      <rdw212:DTim xsi:type="rdw212:TimeStamp">2026-01-05T19:39:47Z</rdw212:DTim>
      <rdw212:Index xsi:type="xsd:long">0</rdw212:Index>
      <rdw212:Description xsi:type="rdw212:String2000"></rdw212:Description>
     </rdw211:ExtensionNameValue>
     <rdw211:Viscosity xsi:type="rdw211:RheometerViscosity" uid="">
      <rdw211:Speed xsi:type="rdw212:AngularVelocityMeasure" uom="dega/h">0.0</rdw211:Speed>
      <rdw211:Viscosity xsi:type="xsd:double">0.0</rdw211:Viscosity>
     </rdw211:Viscosity>
    </rdw211:Rheometer>
   </rdw211:Fluid>
   <rdw211:Wellbore xsi:type="rdw212:DataObjectReference">
    <rdw212:Uuid xsi:type="rdw212:UuidString"></rdw212:Uuid>
    <rdw212:ObjectVersion xsi:type="rdw212:String64"></rdw212:ObjectVersion>
    <rdw212:QualifiedType xsi:type="rdw212:QualifiedType"></rdw212:QualifiedType>
    <rdw212:Title xsi:type="rdw212:String2000"></rdw212:Title>
    <rdw212:EnergisticsUri xsi:type="xsd:anyURI">http://www.example.com/schema/anyURI</rdw212:EnergisticsUri>
    <rdw212:LocatorUrl xsi:type="xsd:anyURI">http://www.example.com/schema/anyURI</rdw212:LocatorUrl>
    <rdw212:ExtensionNameValue xsi:type="rdw212:ExtensionNameValue">
     <rdw212:Name xsi:type="rdw212:String64"></rdw212:Name>
     <rdw212:Value xsi:type="rdw212:StringMeasure" uom=""></rdw212:Value>
     <rdw212:MeasureClass xsi:type="rdw212:MeasureClass">absorbed dose</rdw212:MeasureClass>
     <rdw212:DTim xsi:type="rdw212:TimeStamp">2026-01-05T19:39:47Z</rdw212:DTim>
     <rdw212:Index xsi:type="xsd:long">0</rdw212:Index>
     <rdw212:Description xsi:type="rdw212:String2000"></rdw212:Description>
    </rdw212:ExtensionNameValue>
   </rdw211:Wellbore>
  </rdw211:FluidsReport>

